freqprob/__init__.py
freqprob/advanced.py
freqprob/base.py
freqprob/basic.py
freqprob/cache.py
freqprob/lazy.py
freqprob/lidstone.py
freqprob/memory_efficient.py
freqprob/profiling.py
freqprob/py.typed
freqprob/smoothing.py
freqprob/streaming.py
freqprob/utils.py
freqprob/validation.py
freqprob/vectorized.py
freqprob-0.2.0.dist-info/METADATA
freqprob-0.2.0.dist-info/WHEEL
freqprob-0.2.0.dist-info/licenses/LICENSE
freqprob-0.2.0.dist-info/RECORD
