Metadata-Version: 2.4
Name: freqprob
Version: 0.2.0
Summary: A Python library for scoring observation probabilities from frequency counts, with multiple smoothing methods.
Project-URL: Homepage, https://github.com/tresoldi/freqprob
Project-URL: Documentation, https://github.com/tresoldi/freqprob/blob/main/docs/user_guide.md
Project-URL: Repository, https://github.com/tresoldi/freqprob.git
Project-URL: Issues, https://github.com/tresoldi/freqprob/issues
Project-URL: Changelog, https://github.com/tresoldi/freqprob/blob/main/CHANGELOG.md
Author-email: Tiago Tresoldi <tiago.tresoldi@lingfil.uu.se>
Maintainer-email: Tiago Tresoldi <tiago.tresoldi@lingfil.uu.se>
License:                     GNU GENERAL PUBLIC LICENSE
License-File: LICENSE
Keywords: frequency,language-model,nlp,probability,smoothing
Classifier: Development Status :: 4 - Beta
Classifier: Intended Audience :: Developers
Classifier: Intended Audience :: Science/Research
Classifier: License :: OSI Approved :: MIT License
Classifier: Operating System :: OS Independent
Classifier: Programming Language :: Python
Classifier: Programming Language :: Python :: 3
Classifier: Programming Language :: Python :: 3.10
Classifier: Programming Language :: Python :: 3.11
Classifier: Programming Language :: Python :: 3.12
Classifier: Programming Language :: Python :: Implementation :: CPython
Classifier: Programming Language :: Python :: Implementation :: PyPy
Classifier: Topic :: Scientific/Engineering
Classifier: Topic :: Scientific/Engineering :: Artificial Intelligence
Classifier: Topic :: Text Processing :: Linguistic
Classifier: Typing :: Typed
Requires-Python: >=3.10
Requires-Dist: numpy>=1.20.0
Requires-Dist: scipy>=1.7.0
Provides-Extra: all
Requires-Dist: hypothesis>=6.0.0; extra == 'all'
Requires-Dist: jupyter>=1.0.0; extra == 'all'
Requires-Dist: matplotlib>=3.5.0; extra == 'all'
Requires-Dist: nltk>=3.8; extra == 'all'
Requires-Dist: psutil>=5.8.0; extra == 'all'
Requires-Dist: scikit-learn>=1.0.0; extra == 'all'
Requires-Dist: seaborn>=0.11.0; extra == 'all'
Provides-Extra: dev
Requires-Dist: bandit[toml]>=1.7.5; extra == 'dev'
Requires-Dist: black>=23.0.0; extra == 'dev'
Requires-Dist: build>=0.10.0; extra == 'dev'
Requires-Dist: flake8; extra == 'dev'
Requires-Dist: hatch>=1.7.0; extra == 'dev'
Requires-Dist: hypothesis>=6.0.0; extra == 'dev'
Requires-Dist: isort>=5.12.0; extra == 'dev'
Requires-Dist: mkdocs-material>=9.0.0; extra == 'dev'
Requires-Dist: mkdocs>=1.5.0; extra == 'dev'
Requires-Dist: mkdocstrings[python]>=0.20.0; extra == 'dev'
Requires-Dist: mypy>=1.5.0; extra == 'dev'
Requires-Dist: nltk>=3.8; extra == 'dev'
Requires-Dist: pre-commit>=3.0.0; extra == 'dev'
Requires-Dist: pydocstyle>=6.0.0; extra == 'dev'
Requires-Dist: pytest-cov>=4.0.0; extra == 'dev'
Requires-Dist: pytest-xdist>=3.0.0; extra == 'dev'
Requires-Dist: pytest>=7.0.0; extra == 'dev'
Requires-Dist: ruff>=0.1.0; extra == 'dev'
Requires-Dist: scikit-learn>=1.0.0; extra == 'dev'
Requires-Dist: twine>=4.0.0; extra == 'dev'
Provides-Extra: memory
Requires-Dist: psutil>=5.8.0; extra == 'memory'
Provides-Extra: notebook
Requires-Dist: jupyter>=1.0.0; extra == 'notebook'
Requires-Dist: matplotlib>=3.5.0; extra == 'notebook'
Requires-Dist: seaborn>=0.11.0; extra == 'notebook'
Provides-Extra: validation
Requires-Dist: hypothesis>=6.0.0; extra == 'validation'
Requires-Dist: nltk>=3.8; extra == 'validation'
Requires-Dist: scikit-learn>=1.0.0; extra == 'validation'
